odoo9_addon_openeducat_placement-9.0.2.4.0-py2.7-nspkg.pth
odoo9_addon_openeducat_placement-9.0.2.4.0.dist-info/top_level.txt
odoo9_addon_openeducat_placement-9.0.2.4.0.dist-info/WHEEL
odoo9_addon_openeducat_placement-9.0.2.4.0.dist-info/RECORD
odoo9_addon_openeducat_placement-9.0.2.4.0.dist-info/metadata.json
odoo9_addon_openeducat_placement-9.0.2.4.0.dist-info/DESCRIPTION.rst
odoo9_addon_openeducat_placement-9.0.2.4.0.dist-info/METADATA
odoo9_addon_openeducat_placement-9.0.2.4.0.dist-info/namespace_packages.txt
odoo_addons/openeducat_placement/placement_menu.xml
odoo_addons/openeducat_placement/__openerp__.py
odoo_addons/openeducat_placement/__init__.py
odoo_addons/openeducat_placement/security/ir.model.access.csv
odoo_addons/openeducat_placement/models/__init__.py
odoo_addons/openeducat_placement/models/placement.py
odoo_addons/openeducat_placement/i18n/openeducat_placement.pot
odoo_addons/openeducat_placement/views/placement_view.xml
odoo_addons/openeducat_placement/demo/op.placement.offer.csv
odoo_addons/openeducat_placement/static/description/openeducat_logo.png
odoo_addons/openeducat_placement/static/description/placement.png
odoo_addons/openeducat_placement/static/description/index.html
odoo_addons/openeducat_placement/static/description/openeducat_placement_banner.jpg
odoo_addons/openeducat_placement/static/description/icon.png
